<Properties StartupConfiguration="{C910001F-77E4-F3B6-69DF-48B608188AD2}|">
  <MonoDevelop.Ide.Workspace ActiveConfiguration="Debug" />
  <MultiItemStartupConfigurations />
  <MonoDevelop.Ide.ItemProperties.Assembly-CSharp PreferredExecutionTarget="b469aea6-7380-47c3-80f1-807c93a31615" />
  <MonoDevelop.Ide.DebuggingService.Breakpoints>
    <BreakpointStore />
  </MonoDevelop.Ide.DebuggingService.Breakpoints>
  <MonoDevelop.Ide.Workbench ActiveDocument="Assets/Scripts/MenuController.cs">
    <Files>
      <File FileName="Assets/Scripts/PlayerInteraction.cs" Line="1" Column="1" />
      <File FileName="Assets/Scripts/GameManager.cs" Line="114" Column="13" />
      <File FileName="Assets/Scripts/EventManager.cs" Line="35" Column="24" />
      <File FileName="Assets/Scripts/MenuController.cs" Line="58" Column="9" />
    </Files>
    <Pads>
      <Pad Id="ProjectPad">
        <State name="__root__">
          <Node name="MyProject-ON" expanded="True">
            <Node name="Assets" expanded="True">
              <Node name="GUI Items" expanded="True" />
              <Node name="Scripts" expanded="True">
                <Node name="OtherScripts" expanded="True" />
              </Node>
              <Node name="VLights" expanded="True">
                <Node name="Editor" expanded="True" />
              </Node>
            </Node>
          </Node>
        </State>
      </Pad>
    </Pads>
  </MonoDevelop.Ide.Workbench>
  <MonoDevelop.Ide.DebuggingService.PinnedWatches />
</Properties>